P1/sintetizable/src/design.sv
module FIFO_no_sintetizable
#(parameter DEPTH=32, parameter WIDTH=8)

//pasamelo a formato no ansi c
(CLOCK, RESET_N, CLEAR_N, DATA_IN, READ, WRITE, DATA_OUT, USE_DW, F_EMPTY_N, F_FULL_N);
	  // FIFO interface signals
    input 	logic CLOCK;//!reloj de sistema
    input  logic RESET_N; //!reset asíncrono activo en bajo
    input  logic CLEAR_N; //!limpia la fifo, activo en bajo
    input  logic [WIDTH-1:0] DATA_IN; //!dato a escribir en la fifo
    input  logic READ; //!señal de lectura
    input  logic WRITE; //!señal de escritura
    output logic [WIDTH-1:0] DATA_OUT; //!dato leido de la fifo
    output logic [$clog2(DEPTH):0] USE_DW; //!número de palabras usadas en la fifo
    output logic F_EMPTY_N; //!fifo vacía activo a nivel bajo
    output logic F_FULL_N; //!fifo llena activo a nivel bajo
  

  
  
  logic [WIDTH-1:0] cola [$:DEPTH] ;


  
always_ff @(negedge RESET_N, posedge CLOCK)
if (!RESET_N)
begin
  cola.delete(); 
  DATA_OUT<='0;
end
else
if (!CLEAR_N)
begin
  cola.delete();
  DATA_OUT<='0;
end
else
  begin
    case ({READ,WRITE})
      2'b01: if (cola.size()<DEPTH) cola.push_front(DATA_IN);
      2'b10: DATA_OUT<=cola.pop_back(); 
      2'b11: begin 

              cola.push_front(DATA_IN);              
              DATA_OUT<=cola.pop_back(); 
            end

    endcase

  end

  assign  USE_DW=cola.size();
  assign  F_FULL_N=!(cola.size()==DEPTH);
  assign  F_EMPTY_N=!(cola.size()==0); 
     

property  llenado ;
    (@(posedge CLOCK) not (WRITE==1'b1 && F_FULL_N==1'b0 &&READ==1'b0));
endproperty
sobrellenado:assert property (llenado)  else $error("estas escribiendo sobre una fifo llena");

property  vaciado ;
  (@(posedge CLOCK) not (READ==1'b1 && F_EMPTY_N==1'b0&& WRITE==1'b0)) ;
endproperty
sobrevaciado:assert property  (vaciado) else $error("estas leyendo de una fifo vacia");
  

endmodule

P1/sesion1/src/testbench.sv
// Code`timescale 1 ns/ 1 ps

module FIFO_tb_v0();

parameter DEPTH=32, WIDTH=8;
localparam ADDRESS=$clog2(DEPTH);
 
logic  clock, reset, rden,wren,clear;
logic  [WIDTH-1:0] data_in;
logic  [ADDRESS:0] use_dw;



logic [4:0] rdaddress;

logic [4:0] wraddress;

logic full,empty;                                              
logic [WIDTH-1:0]  data_out;
  



//Modelo de la FIFO

logic [7:0] FIFO_ideal [$]; //Definida con una cola
mailbox FIFO_ideal_mbox = new(); //definida con un mailbox

// Instancia del DUV
FIFO_no_sintetizable DUV (.CLOCK(clock),
               .RESET_N(reset),
               .DATA_IN(data_in),
               .READ(rden),
               .WRITE(wren),
               .CLEAR_N(1'b1),
               .F_FULL_N(full),
               .F_EMPTY_N(empty),
			   .USE_DW(use_dw),
               .DATA_OUT(data_out));





// Casos de Test	  
initial
begin
$info("INICIO VALIDACION");
inicializacion();

$info("*** TEST 1: Escritura simple");
test_A();
$info("*** FIN TEST 1 ****");



$info   ("*** TEST 2: LLenado simple de la FIFO");
resetON();
llenar_simple();
$info("*** FIN TEST 2 ****");

$info("*** TEST 3: Escritura y lectura simultanea con FIFO vacia");
resetON();
lectura_escritura(10,10);
$info("*** FIN TEST 3 ****");

$info("*** TEST 3: Escritura y lectura simultanea con FIFO llena");
resetON();
test_B();
$info("*** FIN TEST 3 ****");

$info("*** TEST 4: Llenado y vaciado de la FIFO");
resetON();
test_C();
$info("*** FIN TEST 4 ****");

$info("*** TEST 5: Escritura y lectura aleatoria con FIFO vacia, llena y a mitad.");
resetON();
test_D();
$info("*** FIN TEST 5 ****");


repeat(5) @(posedge clock);
$info("FIN VALIDACION");

$stop;
end


initial begin
  $dumpfile("FIFO_TB.vcd");
  $dumpvars(0,FIFO_tb_v0.DUV);
end  
        

assign clear = 1'b1;
// Generación de reloj
initial                                                
begin   
 clock = 1'b0;                                               
 forever #10 clock = !clock;                    
end




// Inicialización de las entradas 	
task init_inputs();
begin
  data_in <='0;
  wren <= 1'b0;
  rden <= 1'b0;
end
endtask
// Generación de reset
task resetON();
begin
#10 reset=1'b0;
FIFO_ideal={};
repeat(5) @(posedge clock);
#7 reset=1'b1;
end
endtask

// Escritura de datos en la FIFO. 
// La entrada define el número de datos a escribir   
task solo_escritura(input integer n_escrituras);
begin
logic [7:0] dato;
wren<=1'b0;
@(negedge clock) 
wren<=1'b1;
repeat (n_escrituras) begin
 dato = $random%256;
 data_in = dato;
 FIFO_ideal.push_front(dato);
 @(negedge clock);
end
wren <= 1'b0;
end
endtask
// Lectura de datos de la FIFO, el número de datos a leer
// Monitoriza la salida.
task solo_lectura(input integer n_lecturas);
logic [7:0] dato;
begin
  rden <= 1'b0;
  @(negedge clock);
  rden <= 1'b1;
  repeat (n_lecturas) begin 
    @(negedge clock);
    dato = FIFO_ideal.pop_back();
    assert (dato == data_out) else $error("ERROR el dato leido %h no coincide con el esperado %h", dato, data_out);
  end
  rden <= 1'b0;
end
endtask
// Lectura y escritura de datos simultanea. Se definen cuantos datos a leer y a escribir.
task lectura_escritura( input integer n_lecturas, input integer n_escrituras);
fork
solo_escritura(n_escrituras);
solo_lectura(n_lecturas);
join
endtask



    //Monitor de palabras en la fifo
    // palabras en la fifo
integer palabras;
always @(posedge clock, negedge reset)
if (!reset) palabras=0;
    else if (!clear) palabras=0;
else 
   case({wren,rden})
   2'b01: palabras = palabras-1;
   2'b10: palabras = palabras+1;
   endcase
// Asserciones de control de la FIFO

   always @(negedge clock)
begin
if (reset && clear) begin
   assert ((!empty)?(palabras == 0):(palabras != 0)) else $error("ERROR señal de FIFO vacía activada incorrectamente");
   assert ((!full)? (palabras == 32):(palabras != 32)) else $error("ERROR señal de FIFO llena activada incorrectamente");
   assert (palabras <= 32) else $error("ERROR FIFO con tamaño  incorrecto");
  assert (palabras[5:0] == use_dw) else $error("ERROR USE_DW no funciona como se espera");
end
end


//empiezan los tasks de alto nivel:casos de test


task inicializacion;
begin
$display("Inicializacion de las entradas");
init_inputs;
$display(" reset inicial");
resetON();
end
endtask

// Escritura simple de dos valores y una lectura.
task test_A;
begin
$display(" escribo dos valores");
solo_escritura(1);
solo_escritura(1);
$display("leo un valor");
solo_lectura(1);
end
endtask

// Escritura y lectura simultanea con fifo llena.
task test_B;
begin
llenar_simple;
lectura_escritura(10,10);
end
endtask

// Test de llenado y vaciado.
task test_C;
begin

llenar_simple;
vaciado_simple();
lectura_escritura(10,10);
end
endtask



task test_D;
begin
  vaciado_simple();
  rd_wr_random(100);
  llenar_simple;
  rd_wr_random(100);
  vaciado_simple();
  solo_escritura(15);
  rd_wr_random(100);
end
endtask

 // Escrituras y lecturas aleatorias.
 task rd_wr_random(integer numero);
 begin
   integer caso;   
   repeat(numero) begin
   caso = $random%3;
   case (caso)
    0: if (empty) solo_lectura(1);
    1: if (full) solo_escritura(1);
    2:  lectura_escritura(1,1);
    endcase
   end
 end
 
endtask

// Task de llenado de la FIFO
task llenar_simple();
logic [7:0]cuenta;
begin
 cuenta=8'b0;
  while (full==1'b1)
 begin
  solo_escritura(1);
  cuenta++;
 end
  
end
endtask

// Task de vaciado de la FIFO
task vaciado_simple();
logic [7:0]cuenta;
begin
 cuenta<=8'b0;
 while (empty==1'b1)
 begin
  solo_lectura(1);
  cuenta++;
 end
 
 
end
endtask
endmodule 
// or browse Examples

P1/sesion1/sim/FIFO_TB.vcd
$date
	Tue Sep 15 19:36:53 2026
$end
$version
	QuestaSim Version 2025.1_2
$end
$timescale
	1ns
$end

$scope module FIFO_tb_v0 $end

$scope module DUV $end
$var parameter 32 ! DEPTH $end
$var parameter 32 " WIDTH $end
$var reg 1 # CLOCK $end
$var reg 1 $ RESET_N $end
$var reg 1 % CLEAR_N $end
$var reg 8 & DATA_IN [7:0] $end
$var reg 1 ' READ $end
$var reg 1 ( WRITE $end
$var reg 8 ) DATA_OUT [7:0] $end
$var reg 6 * USE_DW [5:0] $end
$var reg 1 + F_EMPTY_N $end
$var reg 1 , F_FULL_N $end

$scope begin sobrellenado $end
$upscope $end

$scope begin sobrevaciado $end
$upscope $end
$upscope $end
$upscope $end
$enddefinitions $end
#0
$dumpvars
0#
x$
1%
b0 &
0'
0(
bx )
b0 *
0+
1,
b100000 !
b1000 "
$end
#10
1#
0$
b0 )
#20
0#
#30
1#
#40
0#
#50
1#
#60
0#
#70
1#
#80
0#
#90
1#
#97
1$
#100
0#
b100100 &
1(
#110
1#
b1 *
1+
#120
0#
0(
#130
1#
#140
0#
b10000001 &
1(
#150
1#
b10 *
#160
0#
0(
#170
1#
#180
0#
1'
#190
1#
b1 *
b100100 )
#200
0#
0'
#210
0$
1#
b0 *
0+
b0 )
#220
0#
#230
1#
#240
0#
#250
1#
#260
0#
#270
1#
#280
0#
#290
1#
#300
0#
#310
1#
#317
1$
#320
0#
b1001 &
1(
#330
1#
b1 *
1+
#340
0#
0(
#350
1#
#360
0#
b1100011 &
1(
#370
1#
b10 *
#380
0#
0(
#390
1#
#400
0#
b1101 &
1(
#410
1#
b11 *
#420
0#
0(
#430
1#
#440
0#
b10001101 &
1(
#450
1#
b100 *
#460
0#
0(
#470
1#
#480
0#
b1100101 &
1(
#490
1#
b101 *
#500
0#
0(
#510
1#
#520
0#
b10010 &
1(
#530
1#
b110 *
#540
0#
0(
#550
1#
#560
0#
b1 &
1(
#570
1#
b111 *
#580
0#
0(
#590
1#
#600
0#
b1101 &
1(
#610
1#
b1000 *
#620
0#
0(
#630
1#
#640
0#
b1110110 &
1(
#650
1#
b1001 *
#660
0#
0(
#670
1#
#680
0#
b111101 &
1(
#690
1#
b1010 *
#700
0#
0(
#710
1#
#720
0#
b11101101 &
1(
#730
1#
b1011 *
#740
0#
0(
#750
1#
#760
0#
b10001100 &
1(
#770
1#
b1100 *
#780
0#
0(
#790
1#
#800
0#
b11111001 &
1(
#810
1#
b1101 *
#820
0#
0(
#830
1#
#840
0#
b11000110 &
1(
#850
1#
b1110 *
#860
0#
0(
#870
1#
#880
0#
b11000101 &
1(
#890
1#
b1111 *
#900
0#
0(
#910
1#
#920
0#
b10101010 &
1(
#930
1#
b10000 *
#940
0#
0(
#950
1#
#960
0#
b11100101 &
1(
#970
1#
b10001 *
#980
0#
0(
#990
1#
#1000
0#
b1110111 &
1(
#1010
1#
b10010 *
#1020
0#
0(
#1030
1#
#1040
0#
b10010 &
1(
#1050
1#
b10011 *
#1060
0#
0(
#1070
1#
#1080
0#
b10001111 &
1(
#1090
1#
b10100 *
#1100
0#
0(
#1110
1#
#1120
0#
b11110010 &
1(
#1130
1#
b10101 *
#1140
0#
0(
#1150
1#
#1160
0#
b11001110 &
1(
#1170
1#
b10110 *
#1180
0#
0(
#1190
1#
#1200
0#
b11101000 &
1(
